setup.py
beserve/__init__.py
beserve.egg-info/PKG-INFO
beserve.egg-info/SOURCES.txt
beserve.egg-info/dependency_links.txt
beserve.egg-info/not-zip-safe
beserve.egg-info/top_level.txt