Metadata-Version: 1.0
Name: beserve
Version: 0.1
Summary: versatile server emulator
Home-page: https://github.com/perrin-ay/beserve
Author: perrin-ay
Author-email: arnabchat@hotmail.com
License: UNKNOWN
Platform: UNKNOWN
